<?xml version='1.0' encoding='utf-8'?>
<song createdIn="OpenLP 2.4.4" modifiedDate="2016-12-15T13:21:53" modifiedIn="OpenLP 2.4.4" version="0.8" xmlns="http://openlyrics.info/namespace/2009/song"><properties><titles><title>Chorus 216(Biswas Garchu Pukaar Garchu)</title></titles><authors><author>Author Unknown</author></authors></properties><lyrics><verse name="v1"><lines><br/>विश्वास गर्छु, पुकार गर्छु, जीवन म अर्पण गर्छु<br/>तिमीमा, केवल तिमीमा, (केवल येशू तिमीमा) २</lines></verse><verse name="v2"><lines>भरोसा राख्छु, शरण पर्छु, संसारलाई त्यागिदिन्छु<br/>तिमीमा, केवल तिमीमा, (केवल येशू तिमीमा) २</lines></verse><verse name="v3"><lines>सँगै हिँड्छु, क्रूसलाईं अँगाल्छु, मृत्युपारि उदाउँछु<br/>तिमीमा, केवल तिमीमा, (केवल येशू तिमीमा) २ </lines></verse></lyrics></song>