<?xml version='1.0' encoding='utf-8'?>
<song createdIn="OpenLP 2.4.4" modifiedDate="2016-12-15T13:21:53" modifiedIn="OpenLP 2.4.4" version="0.8" xmlns="http://openlyrics.info/namespace/2009/song"><properties><titles><title>Bhajan 345(Khristkai Lagi Sabai)</title></titles><authors><author>Author Unknown</author></authors></properties><lyrics><verse name="v1"><lines><br/>१. ख्रीष्टकै लागि सबै, ख्रीष्टकै काम गर्ने शक्ति मेरो<br/>बात, विचार, कामहरू सबै, दिन, घण्टा सबै मेरो<br/>ख्रीष्टकै लागि सबै ख्रीष्टकै काम गर्ने शक्ति मेरो<br/>ख्रीष्टकै लागि सबै ख्रीष्टकै दिन घण्टा सबै मेरो ।</lines></verse><verse name="v2"><lines>२. उनको कार्य यी हातले गरून्, पाउ उनको पथमा हिँडूँन्<br/>आँखाले ख्रीष्टलाई देखून्, ओठले उनको स्तुति गरून्<br/>ख्रीष्टकै लागि सबै ख्रीष्टकै पाउ उनको पथमा हिँडूँन्<br/>ख्रीष्टकै लागि सबै ख्रीष्टकै ओठले उनको स्तुति गरून् ।</lines></verse><verse name="v3"><lines>३. आँखा जब ख्रीष्टमा लाएँ ख्रीष्ट टाँगिएको देखें<br/>आत्माले ख्रीष्ट मात्र देखें, अरू थोक मैले भुलें<br/>ख्रीष्टकै लागि सबै ख्रीष्टकै, ख्रीष्ट टाँगिएको देखें<br/>ख्रीष्टकै लागि सबै ख्रीष्टकै, अरू थोक मैले भुलें । </lines></verse></lyrics></song>