<?xml version='1.0' encoding='utf-8'?>
<song createdIn="OpenLP 2.4.4" modifiedDate="2016-12-15T13:21:53" modifiedIn="OpenLP 2.4.4" version="0.8" xmlns="http://openlyrics.info/namespace/2009/song"><properties><titles><title>Bhajan 687(Ma Euta Jhareko Paat)</title></titles><authors><author>Author Unknown</author></authors></properties><lyrics><verse name="v1"><lines><br/>कोः म एउटा झरेको पात जस्तै तर प्रभुले उठाउनुभयो (२)</lines></verse><verse name="v2"><lines>१. म अन्धकारमा हिँडेर लड्दै थिएँ<br/>म बाटो विहीन भएर हिँड्दै थिएँ (२)<br/>उज्यालो ज्योति दिई येशूले लिनको निम्ति आउनुभयो</lines></verse><verse name="v3"><lines>२. म संसारको दरिलो बन्धनमा परेको थिएँ<br/>म पापको दास बनेर मर्दै थिएँ (२)<br/>पापको बन्धन तोडी येशूले अनन्त जीवन दिनुभयो । </lines></verse></lyrics></song>