<?xml version='1.0' encoding='utf-8'?>
<song createdIn="OpenLP 2.4.4" modifiedDate="2016-12-15T13:21:53" modifiedIn="OpenLP 2.4.4" version="0.8" xmlns="http://openlyrics.info/namespace/2009/song"><properties><titles><title>Chorus 227(Ma Pokhina Chahanchu)</title></titles><authors><author>Author Unknown</author></authors></properties><lyrics><verse name="v1"><lines><br/>म पोखिन चाहन्छु अर्घ-बलिझैँ, हृदय मेरो चढाई<br/>छुन चाहन्छु तपाईंको हृदय अब सहन सक्दिनँ, दूर रहन धेरै<br/>अँगाल्नुहोस् मलाई, तृप्त बनाउनुहोस् तपाईको प्रेमले । </lines></verse></lyrics></song>